_hycore/__about__.py
_hycore/__init__.py
_hycore/atexit.py
_hycore/better_descriptor.py
_hycore/const.py
_hycore/coro_plus.py
_hycore/decorators.py
_hycore/env_plus.py
_hycore/file.py
_hycore/hash.py
_hycore/import_plus.py
_hycore/io_addons.py
_hycore/json_file.py
_hycore/network.py
_hycore/output_methods.py
_hycore/path.py
_hycore/process.py
_hycore/sys_plus.py
_hycore/threading_methods.py
_hycore/time_.py
_hycore/codedoc/__init__.py
_hycore/codedoc/code_struct.py
_hycore/data_structures/__init__.py
_hycore/data_structures/b_plus_tree.py
_hycore/data_structures/graph.py
_hycore/data_structures/heap.py
_hycore/data_structures/huffman_tree.py
_hycore/data_structures/stack.py
_hycore/data_structures/tree.py
_hycore/data_structures/vis_structure.py
_hycore/data_structures/wrappers.py
_hycore/fsutil/__init__.py
_hycore/fsutil/file.py
_hycore/fsutil/fscopy.py
_hycore/fsutil/hard_link.py
_hycore/fsutil/soft_link.py
_hycore/json/Json.py
_hycore/json/Pickle.py
_hycore/json/__init__.py
_hycore/neostruct/__init__.py
_hycore/neostruct/type_hints.py
_hycore/std_extends/__init__.py
_hycore/std_extends/rich_print.py
_hycore/std_extends/builtin_methods/__init__.py
_hycore/std_extends/builtin_methods/frozen_dict.py
_hycore/typefunc/__init__.py
_hycore/typefunc/binary_tree.py
_hycore/typefunc/bitmap.py
_hycore/typefunc/common.py
_hycore/typefunc/dict_func.py
_hycore/typefunc/errors.py
_hycore/typefunc/function.py
_hycore/typefunc/index_offset.py
_hycore/typefunc/list_func.py
_hycore/typefunc/number.py
_hycore/typefunc/property.py
_hycore/typefunc/safe_eval.py
_hycore/typefunc/tempalte_type.py
_hycore/typefunc/type_func.py
_hycore/utils/__init__.py
_hycore/utils/auto.py
_hycore/utils/basic.py
_hycore/utils/clock.py
_hycore/utils/dotpath.py
_hycore/utils/double_dict.py
_hycore/utils/getting_path.py
_hycore/utils/member_manager.py
_hycore/utils/multi_set.py
_hycore/utils/namespace.py
_hycore/utils/network_packages.py
_hycore/utils/once_message.py
_hycore/utils/permission_manager.py
hydrogenlib_hycore-0.0.2.dist-info/METADATA
hydrogenlib_hycore-0.0.2.dist-info/WHEEL
hydrogenlib_hycore-0.0.2.dist-info/RECORD
